src/__init__.py
src/orchardmanagement_package/__init__.py
src/orchardmanagement_package/fruit_info_operation.py
src/orchardmanagement_package/inventory_operation.py
src/orchardmanagement_package/main.py
src/orchardmanagement_package/plantation_operation.py
src/orchardmanagement_package/sales_operation.py
src/orchardmanagement_package/management/__init__.py
src/orchardmanagement_package/management/inventory.py
src/orchardmanagement_package/management/sales.py
src/orchardmanagement_package/production/__init__.py
src/orchardmanagement_package/production/fruit_info.py
src/orchardmanagement_package/production/plantation.py
test/__init__.py
test/management_test/__init__.py
test/production_test/__init__.py
test/production_test/fruit_test.py
test/production_test/plantingRegion_test.py
unittest_modules/__init__.py
unittest_modules/fruit_unittest.py
unittest_modules/orchard_test_suite.py
unittest_modules/plantation_unittest.py
unittest_modules/unittest_inventory.py
unittest_modules/unittest_sales.py
unittest_modules/management_testing_files/__init__.py
unittest_modules/production_file_test/__init__.py
orchardmanagement_package-0.0.2.dist-info/METADATA
orchardmanagement_package-0.0.2.dist-info/WHEEL
orchardmanagement_package-0.0.2.dist-info/top_level.txt
orchardmanagement_package-0.0.2.dist-info/RECORD
