Metadata-Version: 2.1
Name: orchardmanagement-package
Version: 0.0.2
Summary: orchard management system
Author: Yahan Cong, Kang Lu
Author-email: Yahan Cong <yahan-cong@outlook.com>, Lu Kang <kangluhappy2020@gmail.com>
Project-URL: Homepage, https://github.com/YahanCong/data533_project3
Project-URL: Issues, https://github.com/YahanCong/data533_project3/orchardmanagement
Keywords: python,orchard,orchardmanagement
Classifier: Programming Language :: Python :: 3
Classifier: License :: OSI Approved :: MIT License
Classifier: Operating System :: OS Independent
Requires-Python: >=3.8
